odoo/addons/sale_merge_draft_invoice/README.rst
odoo/addons/sale_merge_draft_invoice/__init__.py
odoo/addons/sale_merge_draft_invoice/__manifest__.py
odoo/addons/sale_merge_draft_invoice/i18n/ca.po
odoo/addons/sale_merge_draft_invoice/i18n/ca_ES.po
odoo/addons/sale_merge_draft_invoice/i18n/de.po
odoo/addons/sale_merge_draft_invoice/i18n/el_GR.po
odoo/addons/sale_merge_draft_invoice/i18n/es.po
odoo/addons/sale_merge_draft_invoice/i18n/es_VE.po
odoo/addons/sale_merge_draft_invoice/i18n/fi.po
odoo/addons/sale_merge_draft_invoice/i18n/fr.po
odoo/addons/sale_merge_draft_invoice/i18n/hr.po
odoo/addons/sale_merge_draft_invoice/i18n/hu.po
odoo/addons/sale_merge_draft_invoice/i18n/it.po
odoo/addons/sale_merge_draft_invoice/i18n/nl.po
odoo/addons/sale_merge_draft_invoice/i18n/pt_BR.po
odoo/addons/sale_merge_draft_invoice/i18n/ro.po
odoo/addons/sale_merge_draft_invoice/i18n/sale_merge_draft_invoice.pot
odoo/addons/sale_merge_draft_invoice/i18n/sl_SI.po
odoo/addons/sale_merge_draft_invoice/i18n/tr.po
odoo/addons/sale_merge_draft_invoice/i18n/vi_VN.po
odoo/addons/sale_merge_draft_invoice/i18n/zh_CN.po
odoo/addons/sale_merge_draft_invoice/model/__init__.py
odoo/addons/sale_merge_draft_invoice/model/res_company.py
odoo/addons/sale_merge_draft_invoice/model/res_config_settings.py
odoo/addons/sale_merge_draft_invoice/model/sale_order.py
odoo/addons/sale_merge_draft_invoice/readme/CONFIGURATION.rst
odoo/addons/sale_merge_draft_invoice/readme/CONTRIBUTORS.rst
odoo/addons/sale_merge_draft_invoice/readme/DESCRIPTION.rst
odoo/addons/sale_merge_draft_invoice/readme/USAGE.rst
odoo/addons/sale_merge_draft_invoice/security/sale_merge_draft_invoice_security.xml
odoo/addons/sale_merge_draft_invoice/static/description/icon.png
odoo/addons/sale_merge_draft_invoice/static/description/index.html
odoo/addons/sale_merge_draft_invoice/tests/__init__.py
odoo/addons/sale_merge_draft_invoice/tests/test_sale_merge_draft_invoice.py
odoo/addons/sale_merge_draft_invoice/view/res_config_settings_views.xml
odoo12_addon_sale_merge_draft_invoice-12.0.1.0.2.dist-info/METADATA
odoo12_addon_sale_merge_draft_invoice-12.0.1.0.2.dist-info/WHEEL
odoo12_addon_sale_merge_draft_invoice-12.0.1.0.2.dist-info/top_level.txt
odoo12_addon_sale_merge_draft_invoice-12.0.1.0.2.dist-info/RECORD
