Metadata-Version: 2.1
Name: odoo12-addon-sale_merge_draft_invoice
Version: 12.0.1.0.2
Summary: Sale Merge Draft Invoice
Home-page: https://github.com/OCA/sale-workflow
Author: Eficent, Odoo Community Association (OCA)
Author-email: support@odoo-community.org
License: LGPL-3
Classifier: Programming Language :: Python
Classifier: Framework :: Odoo
Classifier: Framework :: Odoo :: 12.0
Classifier: License :: OSI Approved :: GNU Lesser General Public License v3 (LGPLv3)
Requires-Python: >=3.5
Requires-Dist: odoo12-addon-sale-order-action-invoice-create-hook
Requires-Dist: odoo<12.1dev,>=12.0a
